refter/__init__.py
refter/cli.py
refter/constants.py
refter/tests/__init__.py
refter/tests/fixtures/manifest.json
refter/tests/fixtures/manifest_bad_refs.json
refter/tests/test_utils.py
refter/types.py
refter/utils/__init__.py
refter/utils/deploy.py
refter/utils/validation.py
refter_cli-0.1.3.dist-info/METADATA
refter_cli-0.1.3.dist-info/WHEEL
refter_cli-0.1.3.dist-info/entry_points.txt
refter_cli-0.1.3.dist-info/RECORD
